django_lite_cms_core-0.0.9.dist-info/licenses/LICENSE
lite_cms_core/__init__.py
lite_cms_core/apps.py
lite_cms_core/managers.py
lite_cms_core/models.py
lite_cms_core/translation.py
lite_cms_core/urls.py
lite_cms_core/views.py
lite_cms_core/locale/de/LC_MESSAGES/django.mo
lite_cms_core/locale/de/LC_MESSAGES/django.po
lite_cms_core/locale/en/LC_MESSAGES/django.mo
lite_cms_core/locale/en/LC_MESSAGES/django.po
lite_cms_core/static/lite_cms_core/css/toolbar.css
lite_cms_core/static/lite_cms_core/icons/chevron-left.svg
lite_cms_core/static/lite_cms_core/icons/chevron-right.svg
lite_cms_core/static/lite_cms_core/icons/pencil-square.svg
lite_cms_core/static/lite_cms_core/icons/search.svg
lite_cms_core/static/lite_cms_core/icons/three-dots.svg
lite_cms_core/static/lite_cms_core/js/toolbar.js
lite_cms_core/templates/lite_cms_core/ext_search_form.html
lite_cms_core/templates/lite_cms_core/search_results.html
lite_cms_core/templates/lite_cms_core/includes/edit_toolbar.html
lite_cms_core/templates/lite_cms_core/includes/search_form.html
lite_cms_core/templatetags/__init__.py
lite_cms_core/templatetags/base_tags.py
lite_cms_core_sample/migrations/0001_initial.py
lite_cms_core_sample/migrations/0002_contentitem.py
lite_cms_core_sample/migrations/__init__.py
lite_cms_core_sample/tests/__init__.py
lite_cms_core_sample/tests/test_base_entity.py
lite_cms_core_sample/tests/test_search_views.py
lite_cms_core_sample/tests/test_slugged_mixin.py
lite_cms_core_sample/tests/test_template_tags.py
django_lite_cms_core-0.0.9.dist-info/METADATA
django_lite_cms_core-0.0.9.dist-info/WHEEL
django_lite_cms_core-0.0.9.dist-info/top_level.txt
django_lite_cms_core-0.0.9.dist-info/RECORD
