Metadata-Version: 2.4
Name: django-lite-cms-core
Version: 0.0.9
Summary: CMS core classes for Django.
Home-page: https://github.com/christianwgd/django-lite-cms-core
Author: Christian Wiegand
License: MIT
Keywords: django,bootstrap,cms
Classifier: Programming Language :: Python :: 3
Classifier: License :: OSI Approved :: MIT License
Classifier: Operating System :: OS Independent
Requires-Python: >=3.10
License-File: LICENSE
Requires-Dist: django
Requires-Dist: django-admin-sortable2
Requires-Dist: django-bootstrap5
Requires-Dist: django-filebrowser-no-grappelli
Requires-Dist: django-tinymce
Requires-Dist: Pillow
Dynamic: author
Dynamic: classifier
Dynamic: description
Dynamic: description-content-type
Dynamic: home-page
Dynamic: keywords
Dynamic: license
Dynamic: license-file
Dynamic: requires-dist
Dynamic: requires-python
Dynamic: summary
